vnsum_eval/__init__.py
vnsum_eval/metrics.py
vnsum_eval/setup.py
vnsum_eval-0.1.2.dist-info/METADATA
vnsum_eval-0.1.2.dist-info/WHEEL
vnsum_eval-0.1.2.dist-info/top_level.txt
vnsum_eval-0.1.2.dist-info/RECORD
